ADBconnect/__init__.py
ADBconnect/action.py
ADBconnect/command.py
ADBconnect/control.py
ADBconnect/screen.py
ADBconnect/servis.py
ADBconnect-0.1.1.dist-info/METADATA
ADBconnect-0.1.1.dist-info/WHEEL
ADBconnect-0.1.1.dist-info/top_level.txt
ADBconnect-0.1.1.dist-info/RECORD
