Metadata-Version: 2.1
Name: ADBconnect
Version: 0.1.1
Summary: Controlling your phone via ADB.
Home-page: https://github.com/Ijidishurka/ADBconnect
Author: Ijidishurka
Project-URL: GitHub, https://github.com/Ijidishurka/ADBconnect
Keywords: adb phone ADB
Classifier: Programming Language :: Python :: 3.11
Classifier: License :: OSI Approved :: MIT License
Classifier: Operating System :: OS Independent
Requires-Python: >=3.6
Requires-Dist: opencv-python
Requires-Dist: numpy
